getkrxcode/__init__.py
getkrxcode/project.py
getkrxcode-0.1.2.dist-info/LICENSE
getkrxcode-0.1.2.dist-info/METADATA
getkrxcode-0.1.2.dist-info/WHEEL
getkrxcode-0.1.2.dist-info/top_level.txt
getkrxcode-0.1.2.dist-info/RECORD
