Metadata-Version: 2.1
Name: getkrxcode
Version: 0.1.2
Summary: a package to get KRX stock code using data.go.kr API
Author-email: kimmh <mluchk@gmail.com>
Project-URL: Homepage, https://github.com/xerxes-k/getkrxcode
Project-URL: Issues, https://github.com/xerxes-k/getkrxcode/issues
Classifier: Programming Language :: Python :: 3
Classifier: License :: OSI Approved :: MIT License
Classifier: Operating System :: OS Independent
Requires-Python: >=3.8
License-File: LICENSE
Requires-Dist: httpx>=0.27.2
Requires-Dist: pandas>=2.2.3
